{"_id":{"$oid":"574c296993187cea02f67617"},"mobile":"13838388438","businessname":"衢州汤面","businessimage":"../img/humberger.jpg","businessaddress":"杭州市余杭区仓前街道仓兴街81号","distance":1.51,"announcement":"吃中饭的亲注意了，中午胆子比较集中，希望大亲们提前预定，谢谢！","commoditytype":"盖浇饭，面条","totalscore":4.1,"servicescore":4,"commodityscore":4.1,"sendmoney":10,"delivermoney":3,"lunchboxmoney":0,"delivertime":40,"monthlyorder":2017}
{"_id":{"$oid":"574c299593187cea02f67619"},"mobile":"1786861111","businessname":"乐而美汉堡（仓兴街店）","businessimage":"../img/humberger.jpg","businessaddress":"杭州市余杭区仓前街道仓兴街300号","distance":1.03,"announcement":"点外卖，上饱了么","commoditytype":"汉堡","totalscore":4.4,"servicescore":4.4,"commodityscore":4.4,"sendmoney":0,"delivermoney":3,"lunchboxmoney":0,"delivertime":40,"monthlyorder":1921}
{"_id":{"$oid":"574c29a393187cea02f6761a"},"mobile":"1786862222","businessname":"高峰黄焖鸡米饭","businessimage":"../img/humberger.jpg","businessaddress":"杭州市余杭区仓前街道仓兴街282号","distance":1.42,"announcement":"做最好的黄焖鸡，有味，实惠","commoditytype":"汉堡","totalscore":4.2,"servicescore":4.2,"commodityscore":4.1,"sendmoney":0,"delivermoney":2,"lunchboxmoney":0,"delivertime":50,"monthlyorder":1834}
{"_id":{"$oid":"574c29b293187cea02f6761b"},"mobile":"1786863333","businessname":"金阳健康餐","businessimage":"../img/humberger.jpg","businessaddress":"杭州市余杭区仓前街道仓兴街123号","distance":1.51,"announcement":"我健康，吃的好","commoditytype":"盖浇饭","totalscore":4.5,"servicescore":4.3,"commodityscore":4.6,"sendmoney":20,"delivermoney":1,"lunchboxmoney":0,"delivertime":30,"monthlyorder":2257}
{"_id":{"$oid":"574c29c193187cea02f6761c"},"mobile":"1786864444","businessname":"子涵餐饭馆","businessimage":"../img/humberger.jpg","businessaddress":"杭州市余杭区仓前街道仓兴街321号","distance":0.828,"announcement":"接受提前预定呀，亲！","commoditytype":"汉堡","totalscore":4.5,"servicescore":4.5,"commodityscore":4.5,"sendmoney":10,"delivermoney":2,"lunchboxmoney":0,"delivertime":34,"monthlyorder":3056}
{"_id":{"$oid":"574c29cf93187cea02f6761d"},"mobile":"1786865555","businessname":"慧珊饺子","businessimage":"../img/humberger.jpg","businessaddress":"杭州市余杭区仓前街道仓兴街34号","distance":0.934,"announcement":"饺子可干捞，水煮，生煎，记得备注哟！","commoditytype":"饺子","totalscore":4.5,"servicescore":4.6,"commodityscore":4.4,"sendmoney":10,"delivermoney":1,"lunchboxmoney":0,"delivertime":40,"monthlyorder":3081}
{"_id":{"$oid":"574c29dc93187cea02f6761e"},"mobile":"1786866666","businessname":"永晖神话","businessimage":"../img/humberger.jpg","businessaddress":"杭州市余杭区仓前街道仓兴街888号","distance":2.37,"announcement":"外卖就属神话好","commoditytype":"各色料理","totalscore":4.8,"servicescore":4.8,"commodityscore":4.8,"sendmoney":15,"delivermoney":1,"lunchboxmoney":0,"delivertime":40,"monthlyorder":6666}
{"_id":{"$oid":"574c29e993187cea02f6761f"},"mobile":"1786867777","businessname":"新味美食","businessimage":"../img/humberger.jpg","businessaddress":"杭州市余杭区仓前街道仓兴街86号","distance":0.775,"announcement":"所有菜品实物实拍","commoditytype":"各色料理","totalscore":4.2,"servicescore":4.1,"commodityscore":4.3,"sendmoney":0,"delivermoney":3,"lunchboxmoney":0,"delivertime":40,"monthlyorder":3612}
{"_id":{"$oid":"574c29f693187cea02f67620"},"mobile":"1786868888","businessname":"炸酱面","businessimage":"../img/humberger.jpg","businessaddress":"杭州市余杭区仓前街道仓兴街43号","distance":1.61,"announcement":"所有菜品实物实拍","commoditytype":"各色料理","totalscore":4.2,"servicescore":4.1,"commodityscore":4.3,"sendmoney":20,"delivermoney":4,"lunchboxmoney":0,"delivertime":40,"monthlyorder":150}
{"_id":{"$oid":"574c2a0293187cea02f67621"},"mobile":"1786869999","businessname":"小神厨","businessimage":"../img/humberger.jpg","businessaddress":"杭州市余杭区仓前街道仓兴街48号","distance":1.6,"announcement":"所有菜品实物实拍","commoditytype":"各色料理","totalscore":4.5,"servicescore":4.5,"commodityscore":4.4,"sendmoney":20,"delivermoney":4,"lunchboxmoney":0,"delivertime":40,"monthlyorder":1687}